torch_harmonics/__init__.py
torch_harmonics/_disco_convolution.py
torch_harmonics/convolution.py
torch_harmonics/legendre.py
torch_harmonics/quadrature.py
torch_harmonics/random_fields.py
torch_harmonics/sht.py
torch_harmonics/distributed/__init__.py
torch_harmonics/distributed/distributed_sht.py
torch_harmonics/distributed/primitives.py
torch_harmonics/distributed/utils.py
torch_harmonics/examples/__init__.py
torch_harmonics/examples/pde_sphere.py
torch_harmonics/examples/shallow_water_equations.py
torch_harmonics/examples/sfno/__init__.py
torch_harmonics/examples/sfno/models/__init__.py
torch_harmonics/examples/sfno/models/activations.py
torch_harmonics/examples/sfno/models/contractions.py
torch_harmonics/examples/sfno/models/factorizations.py
torch_harmonics/examples/sfno/models/layers.py
torch_harmonics/examples/sfno/models/sfno.py
torch_harmonics-0.6.5.dist-info/AUTHORS
torch_harmonics-0.6.5.dist-info/LICENSE
torch_harmonics-0.6.5.dist-info/METADATA
torch_harmonics-0.6.5.dist-info/WHEEL
torch_harmonics-0.6.5.dist-info/top_level.txt
torch_harmonics-0.6.5.dist-info/RECORD
