Metadata-Version: 2.1
Name: torch-harmonics
Version: 0.6.5
Summary: A differentiable spherical harmonic transform for PyTorch.
Home-page: https://github.com/NVIDIA/torch-harmonics
Author: Boris Bonev
Author-email: bbonev@nvidia.com
License: Modified BSD
Platform: UNKNOWN
Classifier: Topic :: Scientific/Engineering
Classifier: License :: OSI Approved :: BSD License
Classifier: Programming Language :: Python :: 3
License-File: LICENSE
License-File: AUTHORS
Requires-Dist: torch
Requires-Dist: numpy
Requires-Dist: triton
Provides-Extra: sfno
Requires-Dist: tensorly ; extra == 'sfno'
Requires-Dist: tensorly-torch ; extra == 'sfno'
